wg_federation/__init__.py
wg_federation/__version__.txt
wg_federation/constants.py
wg_federation/main.py
wg_federation/concurrent_worker/__init__.py
wg_federation/concurrent_worker/worker.py
wg_federation/concurrent_worker/worker_container.py
wg_federation/concurrent_worker/worker_thread.py
wg_federation/concurrent_worker/implementation/__init__.py
wg_federation/concurrent_worker/implementation/wireguard_interface_reload_worker.py
wg_federation/controller/__init__.py
wg_federation/controller/controller_events.py
wg_federation/controller/api/hq_get_private_key_controller.py
wg_federation/controller/baseline/__init__.py
wg_federation/controller/baseline/configure_logging_controller.py
wg_federation/controller/bootstrap/hq_bootstrap_controller.py
wg_federation/crypto/__init__.py
wg_federation/crypto/cryptographic_key_deriver.py
wg_federation/crypto/message_encrypter.py
wg_federation/crypto/message_signer.py
wg_federation/crypto/wireguard_key_generator.py
wg_federation/crypto/data/encrypted_message.py
wg_federation/data/__init__.py
wg_federation/data/input/__init__.py
wg_federation/data/input/configuration_backend.py
wg_federation/data/input/log_level.py
wg_federation/data/input/raw_options.py
wg_federation/data/input/user_input.py
wg_federation/data/input/command_line/__init__.py
wg_federation/data/input/command_line/argparse_action.py
wg_federation/data/input/command_line/command_line_argument.py
wg_federation/data/input/command_line/command_line_option.py
wg_federation/data/input/command_line/is_argument_data_class.py
wg_federation/data/input/command_line/secret_retreival_method.py
wg_federation/data/state/__init__.py
wg_federation/data/state/federation.py
wg_federation/data/state/hq_state.py
wg_federation/data/state/interface_kind.py
wg_federation/data/state/interface_status.py
wg_federation/data/state/wireguard_configuration.py
wg_federation/data/state/wireguard_interface.py
wg_federation/data/state/wireguard_peer.py
wg_federation/data_transformation/__init__.py
wg_federation-0.8.0.dist-info/LICENSE
wg_federation-0.8.0.dist-info/METADATA
wg_federation-0.8.0.dist-info/NOTICE
wg_federation-0.8.0.dist-info/WHEEL
wg_federation-0.8.0.dist-info/entry_points.txt
wg_federation-0.8.0.dist-info/top_level.txt
wg_federation-0.8.0.dist-info/RECORD
