Metadata-Version: 2.1
Name: wg-federation
Version: 0.8.0
Summary: A client/server tool to securely auto-register peers to a wireguard VPN
Author-email: Anuvu DevOps Team <MTL.DevOps.Team@globaleagle.com>
Maintainer-email: Anuvu DevOps Team <MTL.DevOps.Team@globaleagle.com>
Project-URL: source, https://bitbucket.org/GEE_Media/python-wg-federation
Project-URL: container, https://bitbucket.org/GEE_Media/container-wg-federation
Keywords: wireguard,vpn,federation,radius
Classifier: Development Status :: 3 - Alpha
Classifier: Environment :: Console
Classifier: Intended Audience :: System Administrators
Classifier: Topic :: System :: Networking
Classifier: License :: OSI Approved :: Apache Software License
Classifier: Operating System :: POSIX
Classifier: Programming Language :: Python :: 3.9
Classifier: Programming Language :: Python :: 3.10
Classifier: Programming Language :: Python :: 3.11
Classifier: Programming Language :: Python :: 3 :: Only
Requires-Python: >=3.9
License-File: LICENSE
License-File: NOTICE
Requires-Dist: deepmerge (==1.*)
Requires-Dist: dependency-injector (==4.*)
Requires-Dist: ipaddr (==2.*)
Requires-Dist: portalocker (==2.*)
Requires-Dist: pycryptodomex (==3.*)
Requires-Dist: pydantic (==1.*)
Requires-Dist: pynacl (==1.*)
Requires-Dist: pyyaml (==6.*)
Requires-Dist: xdg (==5.*)
Provides-Extra: build
Requires-Dist: setuptools ; extra == 'build'
Requires-Dist: build ; extra == 'build'
Requires-Dist: wheel ; extra == 'build'
Requires-Dist: twine ; extra == 'build'
Requires-Dist: tomli ; extra == 'build'
Requires-Dist: sphinx ; extra == 'build'
Requires-Dist: sphinx-rtd-theme ; extra == 'build'
Provides-Extra: ci
Requires-Dist: wg-federation[build,dev] ; extra == 'ci'
Provides-Extra: dev
Requires-Dist: behave ; extra == 'dev'
Requires-Dist: mockito ; extra == 'dev'
Requires-Dist: bandit ; extra == 'dev'
Requires-Dist: bandit[toml] ; extra == 'dev'
Requires-Dist: pytest (>=7) ; extra == 'dev'
Requires-Dist: pytest-pep8 ; extra == 'dev'
Requires-Dist: pytest-cov ; extra == 'dev'
Requires-Dist: pytest-spec ; extra == 'dev'
Requires-Dist: pre-commit ; extra == 'dev'
Requires-Dist: pylint ; extra == 'dev'
Provides-Extra: dev-with-systemd
Requires-Dist: wg-federation[dev] ; extra == 'dev-with-systemd'
Requires-Dist: systemd-python ; extra == 'dev-with-systemd'
